[
{
    "key": "TES-1",
    "summary": "task 5",
    "description": null,
    "statusId": "10000",
    "typeId": "10002",
    "selfUrl": "https://derui.atlassian.net/rest/api/3/issue/10050",
    "links": [
      {"id": "10", "inwardIssue": "TES-1", "outwardIssue": "TES-2"}
    ],
    "subtasks": []
},
{
    "key": "TES-2",
    "summary": "task 5",
    "description": null,
    "statusId": "10000",
    "typeId": "10002",
    "selfUrl": "https://derui.atlassian.net/rest/api/3/issue/10050",
    "links": [
      {"id": "11", "inwardIssue": "TES-2", "outwardIssue": "TES-3"},
      {"id": "10", "inwardIssue": "TES-1", "outwardIssue": "TES-2"}
    ],
    "subtasks": []
},
 {
    "key": "TES-3",
    "summary": "task 5",
    "description": null,
    "statusId": "10000",
    "typeId": "10002",
    "selfUrl": "https://derui.atlassian.net/rest/api/3/issue/10050",
    "links": [
      {"id": "11", "inwardIssue": "TES-2", "outwardIssue": "TES-3"}
    ],
    "subtasks": []
 }
]
